{
  "refresh_token": "3",
  "format_token": "seats",

  "schedule": [
    {
      "dr": "Dr. Mohamed Saad",
      "subject": "Linear Algebra",
      "from": "10:00",
      "to": "12:00"
    },
    {
      "dr": "Dr. Ahmed Elshaer",
      "subject": "Data Structures",
      "from": "12:30",
      "to": "14:00"
    }
  ],
 "seats": {
  "name": "Dr. Ali Fahmy",
  "title": "Dean",
  "department": "College of AI",
  "country": "Egypt"
  },
  "talk": {
    "speaker": "Prof. Andrew",
    "from": "14:00",
    "to": "15:00"
  },
"meeting": {
    "subject": "Research Collaboration",
    "from": "16:00",
    "to": "17:00"
    
}
}
















